mcp_youtube_search/__init__.py
mcp_youtube_search/cli.py
mcp_youtube_search/server.py
mcp_youtube_search-0.1.4.dist-info/licenses/LICENSE
mcp_youtube_search-0.1.4.dist-info/METADATA
mcp_youtube_search-0.1.4.dist-info/WHEEL
mcp_youtube_search-0.1.4.dist-info/entry_points.txt
mcp_youtube_search-0.1.4.dist-info/top_level.txt
mcp_youtube_search-0.1.4.dist-info/RECORD
