Metadata-Version: 2.4
Name: mcp-youtube-search
Version: 0.1.4
Summary: A YouTube search MCP server for AI agents
Author-email: Arjun Prabhulal <code.aicloudlab@gmail.com>
Project-URL: Homepage, https://github.com/arjunprabhulal/mcp-youtube-search
Project-URL: Bug Tracker, https://github.com/arjunprabhulal/mcp-youtube-search/issues
Classifier: Programming Language :: Python :: 3
Classifier: License :: OSI Approved :: MIT License
Classifier: Operating System :: OS Independent
Requires-Python: >=3.8
License-File: LICENSE
Requires-Dist: google-adk
Requires-Dist: mcp-server
Requires-Dist: python-dotenv
Requires-Dist: google-search-results
Dynamic: license-file
